nameko_proxy/__init__.py
nameko_proxy/proxy.py
nameko_proxy/queue_consumer.py
nameko_proxy/reply_listener.py
nameko_proxy/wrappers/__init__.py
nameko_proxy/wrappers/flask.py
nameko_proxy-0.0.4.dist-info/DESCRIPTION.rst
nameko_proxy-0.0.4.dist-info/METADATA
nameko_proxy-0.0.4.dist-info/RECORD
nameko_proxy-0.0.4.dist-info/WHEEL
nameko_proxy-0.0.4.dist-info/metadata.json
nameko_proxy-0.0.4.dist-info/top_level.txt
tests/__init__.py
tests/test_proxy.py
